{
  "gameId": 10525,
  "gameTitle": "Patapon",
  "achievements": [
    {
      "achievementId": 227853,
      "title": "Patapons Come Home",
      "description": "Complete the prologue without ever breaking the combo",
      "points": 2,
      "trueRatio": 2,
      "type": "missable",
      "author": "DoctorV",
      "badgeUrl": "https://media.retroachievements.org/Badge/386160.png",
      "numAwarded": 1956,
      "numAwardedHardcore": 1240,
      "displayOrder": 0,
      "memAddr": "0xH00d52054=5_T:0xH00d56ae4=1_I:0xW00d12dc0_0xH00f6c8a4=25_Z:0xH00d172a0=0_I:0xW00d12dc0_N:d0xH00f6c8a4!=0_I:0xW00d12dc0_P:0xH00f6c8a4=0.1."
    },
    {
      "achievementId": 227854,
      "title": "Hunting on Patata Plain",
      "description": "Complete - Hunting on Patata Plain -",
      "points": 1,
      "trueRatio": 1,
      "type": "progression",
      "author": "DoctorV",
      "badgeUrl": "https://media.retroachievements.org/Badge/386162.png",
      "numAwarded": 2229,
      "numAwardedHardcore": 1401,
      "displayOrder": 0,
      "memAddr": "0xHd52054=6_d0xHd56ae4=0_0xHd56ae4=1"
    },
    {
      "achievementId": 227855,
      "title": "Escape from Isolation",
      "description": "Complete - Escape from Isolation -",
      "points": 1,
      "trueRatio": 1,
      "type": "progression",
      "author": "DoctorV",
      "badgeUrl": "https://media.retroachievements.org/Badge/386163.png",
      "numAwarded": 1666,
      "numAwardedHardcore": 1080,
      "displayOrder": 0,
      "memAddr": "0xHd52054=7_d0xHd56ae4=0_0xHd56ae4=1"
    },
    {
      "achievementId": 227856,
      "title": "Zigotons Strike Back",
      "description": "Complete - Zigotons Strike Back -",
      "points": 2,
      "trueRatio": 2,
      "type": "progression",
      "author": "DoctorV",
      "badgeUrl": "https://media.retroachievements.org/Badge/386165.png",
      "numAwarded": 1270,
      "numAwardedHardcore": 840,
      "displayOrder": 0,
      "memAddr": "0xHd52054=8_d0xHd56ae4=0_0xHd56ae4=1"
    },
    {
      "achievementId": 227857,
      "title": "Crack the Zigoton Fort!",
      "description": "Complete - Crack the Zigoton Fort! -",
      "points": 2,
      "trueRatio": 3,
      "type": "progression",
      "author": "DoctorV",
      "badgeUrl": "https://media.retroachievements.org/Badge/386166.png",
      "numAwarded": 1086,
      "numAwardedHardcore": 736,
      "displayOrder": 0,
      "memAddr": "0xHd52054=9_d0xHd56ae4=0_0xHd56ae4=1"
    },
    {
      "achievementId": 227858,
      "title": "Gong the Hawkeye",
      "description": "Complete - Gong the Hawkeye -",
      "points": 3,
      "trueRatio": 4,
      "type": "progression",
      "author": "DoctorV",
      "badgeUrl": "https://media.retroachievements.org/Badge/386167.png",
      "numAwarded": 1026,
      "numAwardedHardcore": 697,
      "displayOrder": 0,
      "memAddr": "0xHd52054=10_d0xHd56ae4=0_0xHd56ae4=1"
    },
    {
      "achievementId": 227859,
      "title": "Ancestral Guardian",
      "description": "Complete - Ancestral Guardian - without losing a unit",
      "points": 5,
      "trueRatio": 10,
      "type": "missable",
      "author": "DoctorV",
      "badgeUrl": "https://media.retroachievements.org/Badge/386168.png",
      "numAwarded": 676,
      "numAwardedHardcore": 481,
      "displayOrder": 0,
      "memAddr": "0xHd52054=11_0xHd56bc4=1_0xHd56b2c=0_d0xHd56ae4=0_0xHd56ae4=1_0xHd172a0=1_O:0xXd53b0c!=20_O:0xXd53b14!=20_O:0xXd53b1c!=20_O:0xXd53b24!=20_O:0xXd53b2c!=20_O:0xXd53b34!=20_O:0xXd53b3c!=20_O:0xXd53b44!=20_O:0xXd53b4c!=20_0xXd53b54!=20"
    },
    {
      "achievementId": 227860,
      "title": "Miracle of Lostdon",
      "description": "Complete - Miracle of Lostdon - without losing a unit",
      "points": 5,
      "trueRatio": 11,
      "type": "missable",
      "author": "DoctorV",
      "badgeUrl": "https://media.retroachievements.org/Badge/386169.png",
      "numAwarded": 595,
      "numAwardedHardcore": 420,
      "displayOrder": 0,
      "memAddr": "0xH00d52054=12_0xH00d56bc8=1_0xH00d56b2c=0_d0xH00d56ae4=0_0xH00d56ae4=1_0xH00d172a0=1_O:0xX00d53b0c!=20_O:0xX00d53b14!=20_O:0xX00d53b1c!=20_O:0xX00d53b24!=20_O:0xX00d53b2c!=20_O:0xX00d53b34!=20_O:0xX00d53b3c!=20_O:0xX00d53b44!=20_O:0xX00d53b4c!=20_0xX00d53b54!=20"
    },
    {
      "achievementId": 227861,
      "title": "Desert Crossing",
      "description": "Complete - Desert Crossing -",
      "points": 4,
      "trueRatio": 8,
      "type": "progression",
      "author": "DoctorV",
      "badgeUrl": "https://media.retroachievements.org/Badge/386170.png",
      "numAwarded": 654,
      "numAwardedHardcore": 453,
      "displayOrder": 0,
      "memAddr": "0xHd52054=15_d0xHd56ae4=0_0xHd56ae4=1"
    },
    {
      "achievementId": 227862,
      "title": "Zigotons Attack",
      "description": "Complete - Zigotons Attack -",
      "points": 5,
      "trueRatio": 10,
      "type": "progression",
      "author": "DoctorV",
      "badgeUrl": "https://media.retroachievements.org/Badge/386171.png",
      "numAwarded": 619,
      "numAwardedHardcore": 429,
      "displayOrder": 0,
      "memAddr": "0xHd52054=13_d0xHd56ae4=0_0xHd56ae4=1_0xHd56bcc=0"
    },
    {
      "achievementId": 227863,
      "title": "Desert Behemoth",
      "description": "Complete - Desert Behemoth - without losing a unit",
      "points": 10,
      "trueRatio": 37,
      "type": "missable",
      "author": "DoctorV",
      "badgeUrl": "https://media.retroachievements.org/Badge/386172.png",
      "numAwarded": 277,
      "numAwardedHardcore": 215,
      "displayOrder": 0,
      "memAddr": "0xH00d52054=53_0xH00d56bcc=1_0xH00d56b2c=0_d0xH00d56ae4=0_0xH00d56ae4=1_0xH00d172a0=1_O:0xX00d53b0c!=20_O:0xX00d53b14!=20_O:0xX00d53b1c!=20_O:0xX00d53b24!=20_O:0xX00d53b2c!=20_O:0xX00d53b34!=20_O:0xX00d53b3c!=20_O:0xX00d53b44!=20_O:0xX00d53b4c!=20_0xX00d53b54!=20"
    },
    {
      "achievementId": 227864,
      "title": "Battle for the Oasis",
      "description": "Complete - Battle for the Oasis -",
      "points": 5,
      "trueRatio": 12,
      "type": "progression",
      "author": "DoctorV",
      "badgeUrl": "https://media.retroachievements.org/Badge/386174.png",
      "numAwarded": 496,
      "numAwardedHardcore": 345,
      "displayOrder": 0,
      "memAddr": "0xHd52054=16_d0xHd56ae4=0_0xHd56ae4=1"
    },
    {
      "achievementId": 227865,
      "title": "Gong Returns",
      "description": "Complete - Gong Returns -",
      "points": 5,
      "trueRatio": 13,
      "type": "progression",
      "author": "DoctorV",
      "badgeUrl": "https://media.retroachievements.org/Badge/386175.png",
      "numAwarded": 472,
      "numAwardedHardcore": 326,
      "displayOrder": 0,
      "memAddr": "0xHd52054=17_d0xHd56ae4=0_0xHd56ae4=1"
    },
    {
      "achievementId": 227866,
      "title": "Zigotons Attack Again?!",
      "description": "Complete - Zigotons Attack Again?! -",
      "points": 5,
      "trueRatio": 13,
      "type": "progression",
      "author": "DoctorV",
      "badgeUrl": "https://media.retroachievements.org/Badge/386176.png",
      "numAwarded": 456,
      "numAwardedHardcore": 312,
      "displayOrder": 0,
      "memAddr": "0xHd52054=13_d0xHd56ae4=0_0xHd56ae4=1_0xHd56bcc>=1"
    },
    {
      "achievementId": 227867,
      "title": "Guardian of Knell",
      "description": "Complete - Guardian of Knell - without losing a unit",
      "points": 10,
      "trueRatio": 44,
      "type": "missable",
      "author": "DoctorV",
      "badgeUrl": "https://media.retroachievements.org/Badge/386177.png",
      "numAwarded": 230,
      "numAwardedHardcore": 177,
      "displayOrder": 0,
      "memAddr": "0xH00d52054=54_0xH00d56bd0=1_0xH00d56b2c=0_d0xH00d56ae4=0_0xH00d56ae4=1_0xH00d172a0=1_O:0xX00d53b0c!=20_O:0xX00d53b14!=20_O:0xX00d53b1c!=20_O:0xX00d53b24!=20_O:0xX00d53b2c!=20_O:0xX00d53b34!=20_O:0xX00d53b3c!=20_O:0xX00d53b44!=20_O:0xX00d53b4c!=20_0xX00d53b54!=20"
    },
    {
      "achievementId": 227868,
      "title": "Convoy Escort",
      "description": "Complete - Convoy Escort -",
      "points": 5,
      "trueRatio": 14,
      "type": "progression",
      "author": "DoctorV",
      "badgeUrl": "https://media.retroachievements.org/Badge/386178.png",
      "numAwarded": 441,
      "numAwardedHardcore": 303,
      "displayOrder": 0,
      "memAddr": "0xHd52054=14_d0xHd56ae4=0_0xHd56ae4=1"
    },
    {
      "achievementId": 227869,
      "title": "Ray of Hope",
      "description": "Complete - Ray of Hope -",
      "points": 5,
      "trueRatio": 14,
      "type": "progression",
      "author": "DoctorV",
      "badgeUrl": "https://media.retroachievements.org/Badge/386179.png",
      "numAwarded": 408,
      "numAwardedHardcore": 283,
      "displayOrder": 0,
      "memAddr": "0xHd52054=19_d0xHd56ae4=0_0xHd56ae4=1"
    },
    {
      "achievementId": 227870,
      "title": "Door of Promise",
      "description": "Complete - Door of Promise -",
      "points": 5,
      "trueRatio": 15,
      "type": "progression",
      "author": "DoctorV",
      "badgeUrl": "https://media.retroachievements.org/Badge/386180.png",
      "numAwarded": 386,
      "numAwardedHardcore": 263,
      "displayOrder": 0,
      "memAddr": "0xHd52054=20_d0xHd56ae4=0_0xHd56ae4=1"
    },
    {
      "achievementId": 227871,
      "title": "Battle! Bachikoi Fort",
      "description": "Complete - Battle! Bachikoi Fort -",
      "points": 5,
      "trueRatio": 16,
      "type": "progression",
      "author": "DoctorV",
      "badgeUrl": "https://media.retroachievements.org/Badge/386181.png",
      "numAwarded": 362,
      "numAwardedHardcore": 247,
      "displayOrder": 0,
      "memAddr": "0xHd52054=21_d0xHd56ae4=0_0xHd56ae4=1"
    },
    {
      "achievementId": 227872,
      "title": "Lord of the Mountains",
      "description": "Complete - Lord of the Mountains - without losing a unit",
      "points": 10,
      "trueRatio": 40,
      "type": "missable",
      "author": "DoctorV",
      "badgeUrl": "https://media.retroachievements.org/Badge/386182.png",
      "numAwarded": 272,
      "numAwardedHardcore": 194,
      "displayOrder": 0,
      "memAddr": "0xH00d52054=55_0xH00d56bd4=1_0xH00d56b2c=0_d0xH00d56ae4=0_0xH00d56ae4=1_0xH00d172a0=1_O:0xX00d53b0c!=20_O:0xX00d53b14!=20_O:0xX00d53b1c!=20_O:0xX00d53b24!=20_O:0xX00d53b2c!=20_O:0xX00d53b34!=20_O:0xX00d53b3c!=20_O:0xX00d53b44!=20_O:0xX00d53b4c!=20_0xX00d53b54!=20"
    },
    {
      "achievementId": 227873,
      "title": "Legendary Night Sky",
      "description": "Complete - Legendary Night Sky -",
      "points": 5,
      "trueRatio": 17,
      "type": "progression",
      "author": "DoctorV",
      "badgeUrl": "https://media.retroachievements.org/Badge/386184.png",
      "numAwarded": 342,
      "numAwardedHardcore": 236,
      "displayOrder": 0,
      "memAddr": "0xHd52054=22_d0xHd56ae4=0_0xHd56ae4=1"
    },
    {
      "achievementId": 227874,
      "title": "Awakening at Gayeen",
      "description": "Complete - Awakening at Gayeen - without losing a unit",
      "points": 10,
      "trueRatio": 48,
      "type": "missable",
      "author": "DoctorV",
      "badgeUrl": "https://media.retroachievements.org/Badge/386186.png",
      "numAwarded": 215,
      "numAwardedHardcore": 158,
      "displayOrder": 0,
      "memAddr": "0xH00d52054=56_0xH00d56bd8=1_0xH00d56b2c=0_d0xH00d56ae4=0_0xH00d56ae4=1_0xH00d172a0=1_O:0xX00d53b0c!=20_O:0xX00d53b14!=20_O:0xX00d53b1c!=20_O:0xX00d53b24!=20_O:0xX00d53b2c!=20_O:0xX00d53b34!=20_O:0xX00d53b3c!=20_O:0xX00d53b44!=20_O:0xX00d53b4c!=20_0xX00d53b54!=20"
    },
    {
      "achievementId": 227875,
      "title": "Claws of Guchoppa Ruins",
      "description": "Complete - Claws of Guchoppa Ruins - without losing a unit",
      "points": 10,
      "trueRatio": 56,
      "type": "missable",
      "author": "DoctorV",
      "badgeUrl": "https://media.retroachievements.org/Badge/386187.png",
      "numAwarded": 172,
      "numAwardedHardcore": 133,
      "displayOrder": 0,
      "memAddr": "0xH00d52054=58_0xH00d56be0=1_0xH00d56b2c=0_d0xH00d56ae4=0_0xH00d56ae4=1_0xH00d172a0=1_O:0xX00d53b0c!=20_O:0xX00d53b14!=20_O:0xX00d53b1c!=20_O:0xX00d53b24!=20_O:0xX00d53b2c!=20_O:0xX00d53b34!=20_O:0xX00d53b3c!=20_O:0xX00d53b44!=20_O:0xX00d53b4c!=20_0xX00d53b54!=20"
    },
    {
      "achievementId": 227876,
      "title": "Meden Kidnapped",
      "description": "Complete - Meden Kidnapped -",
      "points": 5,
      "trueRatio": 17,
      "type": "progression",
      "author": "DoctorV",
      "badgeUrl": "https://media.retroachievements.org/Badge/386188.png",
      "numAwarded": 334,
      "numAwardedHardcore": 234,
      "displayOrder": 0,
      "memAddr": "0xHd52054=28_d0xHd56ae4=0_0xHd56ae4=1"
    },
    {
      "achievementId": 227877,
      "title": "Gong Vows to Fight",
      "description": "Complete - Gong Vows to Fight -",
      "points": 10,
      "trueRatio": 38,
      "type": "progression",
      "author": "DoctorV",
      "badgeUrl": "https://media.retroachievements.org/Badge/386189.png",
      "numAwarded": 308,
      "numAwardedHardcore": 210,
      "displayOrder": 0,
      "memAddr": "0xHd52054=23_d0xHd56ae4=0_0xHd56ae4=1"
    },
    {
      "achievementId": 227878,
      "title": "Volcano Guardian",
      "description": "Complete - Volcano Guardian - without losing a unit",
      "points": 10,
      "trueRatio": 48,
      "type": "missable",
      "author": "DoctorV",
      "badgeUrl": "https://media.retroachievements.org/Badge/386190.png",
      "numAwarded": 211,
      "numAwardedHardcore": 158,
      "displayOrder": 0,
      "memAddr": "0xH00d52054=57_0xH00d56bdc=1_0xH00d56b2c=0_d0xH00d56ae4=0_0xH00d56ae4=1_0xH00d172a0=1_O:0xX00d53b0c!=20_O:0xX00d53b14!=20_O:0xX00d53b1c!=20_O:0xX00d53b24!=20_O:0xX00d53b2c!=20_O:0xX00d53b34!=20_O:0xX00d53b3c!=20_O:0xX00d53b44!=20_O:0xX00d53b4c!=20_0xX00d53b54!=20"
    },
    {
      "achievementId": 227879,
      "title": "Across Enemy Territory",
      "description": "Complete - Across Enemy Territory -",
      "points": 5,
      "trueRatio": 20,
      "type": "progression",
      "author": "DoctorV",
      "badgeUrl": "https://media.retroachievements.org/Badge/386191.png",
      "numAwarded": 275,
      "numAwardedHardcore": 188,
      "displayOrder": 0,
      "memAddr": "0xHd52054=24_d0xHd56ae4=0_0xHd56ae4=1"
    },
    {
      "achievementId": 227880,
      "title": "Facing Gate Ghoul Baban",
      "description": "Complete - Facing Gate Ghoul Baban -",
      "points": 10,
      "trueRatio": 43,
      "type": "progression",
      "author": "DoctorV",
      "badgeUrl": "https://media.retroachievements.org/Badge/386192.png",
      "numAwarded": 260,
      "numAwardedHardcore": 179,
      "displayOrder": 0,
      "memAddr": "0xHd52054=25_d0xHd56ae4=0_0xHd56ae4=1"
    },
    {
      "achievementId": 227881,
      "title": "Zigoton Queen",
      "description": "Complete - Zigoton Queen -",
      "points": 5,
      "trueRatio": 21,
      "type": "progression",
      "author": "DoctorV",
      "badgeUrl": "https://media.retroachievements.org/Badge/386193.png",
      "numAwarded": 260,
      "numAwardedHardcore": 179,
      "displayOrder": 0,
      "memAddr": "0xHd52054=26_d0xHd56ae4=0_0xHd56ae4=1"
    },
    {
      "achievementId": 227882,
      "title": "Kharma's Pet",
      "description": "Complete - Kharma's Pet - without losing a unit",
      "points": 10,
      "trueRatio": 48,
      "type": "missable",
      "author": "DoctorV",
      "badgeUrl": "https://media.retroachievements.org/Badge/386201.png",
      "numAwarded": 228,
      "numAwardedHardcore": 159,
      "displayOrder": 0,
      "memAddr": "0xH00d52054=60_0xH00d56be4=1_0xH00d56b2c=0_d0xH00d56ae4=0_0xH00d56ae4=1_0xH00d172a0=1_O:0xX00d53b0c!=20_O:0xX00d53b14!=20_O:0xX00d53b1c!=20_O:0xX00d53b24!=20_O:0xX00d53b2c!=20_O:0xX00d53b34!=20_O:0xX00d53b3c!=20_O:0xX00d53b44!=20_O:0xX00d53b4c!=20_0xX00d53b54!=20"
    },
    {
      "achievementId": 227883,
      "title": "Dark Palace Guardian",
      "description": "Complete - Dark Palace Guardian - without losing a unit",
      "points": 10,
      "trueRatio": 58,
      "type": "missable",
      "author": "DoctorV",
      "badgeUrl": "https://media.retroachievements.org/Badge/386202.png",
      "numAwarded": 176,
      "numAwardedHardcore": 128,
      "displayOrder": 0,
      "memAddr": "0xH00d52054=59_0xH00d56be8=1_0xH00d56b2c=0_d0xH00d56ae4=0_0xH00d56ae4=1_0xH00d172a0=1_O:0xX00d53b0c!=20_O:0xX00d53b14!=20_O:0xX00d53b1c!=20_O:0xX00d53b24!=20_O:0xX00d53b2c!=20_O:0xX00d53b34!=20_O:0xX00d53b3c!=20_O:0xX00d53b44!=20_O:0xX00d53b4c!=20_0xX00d53b54!=20"
    },
    {
      "achievementId": 227884,
      "title": "Final Showdown!",
      "description": "Complete - Final Showdown! -",
      "points": 10,
      "trueRatio": 45,
      "type": "win_condition",
      "author": "DoctorV",
      "badgeUrl": "https://media.retroachievements.org/Badge/386203.png",
      "numAwarded": 250,
      "numAwardedHardcore": 170,
      "displayOrder": 0,
      "memAddr": "0xHd52054=27_d0xHd56ae4=0_0xHd56ae4=1"
    },
    {
      "achievementId": 227885,
      "title": "Servant of Darkness",
      "description": "Complete - Servant of Darkness - without losing a unit",
      "points": 10,
      "trueRatio": 62,
      "type": "missable",
      "author": "DoctorV",
      "badgeUrl": "https://media.retroachievements.org/Badge/386204.png",
      "numAwarded": 154,
      "numAwardedHardcore": 120,
      "displayOrder": 0,
      "memAddr": "0xH00d52054=61_0xH00d56bec=1_0xH00d56b2c=0_d0xH00d56ae4=0_0xH00d56ae4=1_0xH00d172a0=1_O:0xX00d53b0c!=20_O:0xX00d53b14!=20_O:0xX00d53b1c!=20_O:0xX00d53b24!=20_O:0xX00d53b2c!=20_O:0xX00d53b34!=20_O:0xX00d53b3c!=20_O:0xX00d53b44!=20_O:0xX00d53b4c!=20_0xX00d53b54!=20"
    },
    {
      "achievementId": 227886,
      "title": "Fever Till the End",
      "description": "Reach a Fever at the epilogue",
      "points": 2,
      "trueRatio": 10,
      "type": "missable",
      "author": "DoctorV",
      "badgeUrl": "https://media.retroachievements.org/Badge/386205.png",
      "numAwarded": 211,
      "numAwardedHardcore": 148,
      "displayOrder": 0,
      "memAddr": "0xH00d52054=62_I:0xW00d12dc0_T:0xH00f6c8a4=25_0xH00d172a0=1"
    },
    {
      "achievementId": 227887,
      "title": "Ka-ching Really Does Grow on Trees",
      "description": "Find the hidden plant in - Creatures of the Sand -",
      "points": 2,
      "trueRatio": 6,
      "type": "",
      "author": "DoctorV",
      "badgeUrl": "https://media.retroachievements.org/Badge/386206.png",
      "numAwarded": 332,
      "numAwardedHardcore": 245,
      "displayOrder": 0,
      "memAddr": "0xHd52054=43_d0x d56c70=61_0x d56c70=999"
    },
    {
      "achievementId": 227888,
      "title": "Slightly Off",
      "description": "Acquire the Bent Compass",
      "points": 2,
      "trueRatio": 3,
      "type": "",
      "author": "DoctorV",
      "badgeUrl": "https://media.retroachievements.org/Badge/386207.png",
      "numAwarded": 775,
      "numAwardedHardcore": 537,
      "displayOrder": 0,
      "memAddr": "0xHd52054=6_d0xHd39a2c=0_0xHd39a2c=1"
    },
    {
      "achievementId": 227889,
      "title": "The Gardener",
      "description": "Acquire the Zakpon Cap",
      "points": 2,
      "trueRatio": 6,
      "type": "",
      "author": "DoctorV",
      "badgeUrl": "https://media.retroachievements.org/Badge/386208.png",
      "numAwarded": 355,
      "numAwardedHardcore": 258,
      "displayOrder": 0,
      "memAddr": "0xHd52054=43_d0xHd39a60=0_0xHd39a60=1"
    },
    {
      "achievementId": 227890,
      "title": "Musical Spoons",
      "description": "Acquire the Kimpon Cap",
      "points": 2,
      "trueRatio": 5,
      "type": "",
      "author": "DoctorV",
      "badgeUrl": "https://media.retroachievements.org/Badge/386209.png",
      "numAwarded": 441,
      "numAwardedHardcore": 307,
      "displayOrder": 0,
      "memAddr": "0xHd52054=44_d0xHd39a5c=0_0xHd39a5c=1"
    },
    {
      "achievementId": 227891,
      "title": "A Lackluster Shine",
      "description": "Acquire the Dusty Crystal",
      "points": 2,
      "trueRatio": 5,
      "type": "",
      "author": "DoctorV",
      "badgeUrl": "https://media.retroachievements.org/Badge/386210.png",
      "numAwarded": 398,
      "numAwardedHardcore": 282,
      "displayOrder": 0,
      "memAddr": "0xHd52054=44_d0xHd39a34=0_0xHd39a34=1"
    },
    {
      "achievementId": 227892,
      "title": "Favorable Wind",
      "description": "Acquire the Tailwind Miracle",
      "points": 2,
      "trueRatio": 6,
      "type": "",
      "author": "DoctorV",
      "badgeUrl": "https://media.retroachievements.org/Badge/386211.png",
      "numAwarded": 375,
      "numAwardedHardcore": 260,
      "displayOrder": 0,
      "memAddr": "0xHd52054=45_d0xHd39a1c=0_0xHd39a1c=1"
    },
    {
      "achievementId": 227893,
      "title": "The Cook",
      "description": "Acquire the Gashapon Cap",
      "points": 2,
      "trueRatio": 6,
      "type": "",
      "author": "DoctorV",
      "badgeUrl": "https://media.retroachievements.org/Badge/386212.png",
      "numAwarded": 404,
      "numAwardedHardcore": 276,
      "displayOrder": 0,
      "memAddr": "0xHd52054=45_d0xHd39a68=0_0xHd39a68=1"
    },
    {
      "achievementId": 227894,
      "title": "An Ominous Twinkle",
      "description": "Acquire the Black Star",
      "points": 2,
      "trueRatio": 8,
      "type": "",
      "author": "DoctorV",
      "badgeUrl": "https://media.retroachievements.org/Badge/386213.png",
      "numAwarded": 276,
      "numAwardedHardcore": 196,
      "displayOrder": 0,
      "memAddr": "0xHd52054=46_d0xHd39a3c=0_0xHd39a3c=1"
    },
    {
      "achievementId": 227895,
      "title": "The Smith",
      "description": "Acquire the Kampon Cap",
      "points": 2,
      "trueRatio": 8,
      "type": "",
      "author": "DoctorV",
      "badgeUrl": "https://media.retroachievements.org/Badge/386214.png",
      "numAwarded": 250,
      "numAwardedHardcore": 182,
      "displayOrder": 0,
      "memAddr": "0xHd52054=46_d0xHd39a64=0_0xHd39a64=1"
    },
    {
      "achievementId": 227896,
      "title": "Fleeting Guardian Dodonga",
      "description": "Defeat Lv. 10 Dodonga",
      "points": 10,
      "trueRatio": 54,
      "type": "",
      "author": "DoctorV",
      "badgeUrl": "https://media.retroachievements.org/Badge/386215.png",
      "numAwarded": 174,
      "numAwardedHardcore": 140,
      "displayOrder": 0,
      "memAddr": "0xHd52054=11_d0xHd56bc4=9_0xHd56bc4=10"
    },
    {
      "achievementId": 227897,
      "title": "Dauntless Majidonga",
      "description": "Defeat Lv. 10 Majidonga",
      "points": 10,
      "trueRatio": 61,
      "type": "",
      "author": "DoctorV",
      "badgeUrl": "https://media.retroachievements.org/Badge/386216.png",
      "numAwarded": 145,
      "numAwardedHardcore": 122,
      "displayOrder": 0,
      "memAddr": "0xHd52054=12_d0xHd56bc8=9_0xHd56bc8=10"
    },
    {
      "achievementId": 227898,
      "title": "Desert King Zaknel",
      "description": "Defeat Lv. 10 Zaknel",
      "points": 10,
      "trueRatio": 66,
      "type": "",
      "author": "DoctorV",
      "badgeUrl": "https://media.retroachievements.org/Badge/386217.png",
      "numAwarded": 132,
      "numAwardedHardcore": 112,
      "displayOrder": 0,
      "memAddr": "0xHd52054=53_d0xHd56bcc=9_0xHd56bcc=10"
    },
    {
      "achievementId": 227899,
      "title": "Great Dokaknel",
      "description": "Defeat Lv. 10 Dokaknel",
      "points": 10,
      "trueRatio": 70,
      "type": "",
      "author": "DoctorV",
      "badgeUrl": "https://media.retroachievements.org/Badge/386218.png",
      "numAwarded": 120,
      "numAwardedHardcore": 104,
      "displayOrder": 0,
      "memAddr": "0xHd52054=54_d0xHd56bd0=9_0xHd56bd0=10"
    },
    {
      "achievementId": 227900,
      "title": "Stone Goliath Gaeen",
      "description": "Defeat Lv. 10 Gaeen",
      "points": 10,
      "trueRatio": 67,
      "type": "",
      "author": "DoctorV",
      "badgeUrl": "https://media.retroachievements.org/Badge/386219.png",
      "numAwarded": 129,
      "numAwardedHardcore": 110,
      "displayOrder": 0,
      "memAddr": "0xHd52054=55_d0xHd56bd4=9_0xHd56bd4=10"
    },
    {
      "achievementId": 227901,
      "title": "Steel Deity Dogaeen",
      "description": "Defeat Lv. 10 Dogaeen",
      "points": 10,
      "trueRatio": 72,
      "type": "",
      "author": "DoctorV",
      "badgeUrl": "https://media.retroachievements.org/Badge/386220.png",
      "numAwarded": 120,
      "numAwardedHardcore": 102,
      "displayOrder": 0,
      "memAddr": "0xHd52054=56_d0xHd56bd8=9_0xHd56bd8=10"
    },
    {
      "achievementId": 227902,
      "title": "Merciless Crab Queen",
      "description": "Defeat Lv. 10 Ciokina",
      "points": 10,
      "trueRatio": 74,
      "type": "",
      "author": "DoctorV",
      "badgeUrl": "https://media.retroachievements.org/Badge/386221.png",
      "numAwarded": 111,
      "numAwardedHardcore": 98,
      "displayOrder": 0,
      "memAddr": "0xHd52054=57_d0xHd56bdc=9_0xHd56bdc=10"
    },
    {
      "achievementId": 227903,
      "title": "Claws of Cioking",
      "description": "Defeat Lv. 10 Cioking",
      "points": 10,
      "trueRatio": 78,
      "type": "",
      "author": "DoctorV",
      "badgeUrl": "https://media.retroachievements.org/Badge/386222.png",
      "numAwarded": 105,
      "numAwardedHardcore": 93,
      "displayOrder": 0,
      "memAddr": "0xHd52054=58_d0xHd56be0=9_0xHd56be0=10"
    },
    {
      "achievementId": 227904,
      "title": "Carnivorous Shookle",
      "description": "Defeat Lv. 10 Shookle",
      "points": 10,
      "trueRatio": 77,
      "type": "",
      "author": "DoctorV",
      "badgeUrl": "https://media.retroachievements.org/Badge/386223.png",
      "numAwarded": 106,
      "numAwardedHardcore": 95,
      "displayOrder": 0,
      "memAddr": "0xHd52054=60_d0xHd56be4=9_0xHd56be4=10"
    },
    {
      "achievementId": 227905,
      "title": "Insatiable Shooshookle",
      "description": "Defeat Lv. 10 Shooshookle",
      "points": 10,
      "trueRatio": 79,
      "type": "",
      "author": "DoctorV",
      "badgeUrl": "https://media.retroachievements.org/Badge/386224.png",
      "numAwarded": 103,
      "numAwardedHardcore": 92,
      "displayOrder": 0,
      "memAddr": "0xHd52054=59_d0xHd56be8=9_0xHd56be8=10"
    },
    {
      "achievementId": 227906,
      "title": "Two-faced Devil Gorl",
      "description": "Defeat Lv. 10 Gorl",
      "points": 10,
      "trueRatio": 81,
      "type": "",
      "author": "DoctorV",
      "badgeUrl": "https://media.retroachievements.org/Badge/386225.png",
      "numAwarded": 100,
      "numAwardedHardcore": 89,
      "displayOrder": 0,
      "memAddr": "0xHd52054=61_d0xHd56bec=9_0xHd56bec=10"
    },
    {
      "achievementId": 227907,
      "title": "Shake That Bark!",
      "description": "Earn a minimum of 5 items in one session of playing Pakapon's Minigame (Leaves do not count)",
      "points": 5,
      "trueRatio": 13,
      "type": "",
      "author": "DoctorV",
      "badgeUrl": "https://media.retroachievements.org/Badge/386226.png",
      "numAwarded": 448,
      "numAwardedHardcore": 324,
      "displayOrder": 0,
      "memAddr": "N:0xH1ffeba6=85.1._C:d0xHd39a98<0xHd39a98_N:0xH1ffeba6=85.1._C:d0xHd39a9c<0xHd39a9c_N:0xH1ffeba6=85.1._C:d0xHd39aa0<0xHd39aa0_N:0xH1ffeba6=85.1._C:d0xHd39a84<0xHd39a84_N:0xH1ffeba6=85.1._C:d0xHd39a88<0xHd39a88_N:0xH1ffeba6=85.1._C:d0xHd39a8c<0xHd39a8c_0=1.5._R:d0xHd39a74>0xHd39a74_R:d0xHd39a74<0xHd39a74_R:d0xHd39a98>0xHd39a98_R:d0xHd39a9c>0xHd39a9c_R:d0xHd39aa0>0xHd39aa0_R:d0xHd39a84>0xHd39a84_R:d0xHd39a88>0xHd39a88_R:d0xHd39a8c>0xHd39a8c_R:0xHd172a0!=0"
    },
    {
      "achievementId": 227908,
      "title": "Gardening With Care",
      "description": "Earn 3 items in one session of playing Zakpon's Minigame",
      "points": 5,
      "trueRatio": 20,
      "type": "",
      "author": "DoctorV",
      "badgeUrl": "https://media.retroachievements.org/Badge/386227.png",
      "numAwarded": 267,
      "numAwardedHardcore": 195,
      "displayOrder": 0,
      "memAddr": "N:0xH1ffeba6=85.1._C:d0xHd39aa8<0xHd39aa8_N:0xH1ffeba6=85.1._C:d0xHd39aac<0xHd39aac_N:0xH1ffeba6=85.1._C:d0xHd39ab0<0xHd39ab0_N:0xH1ffeba6=85.1._C:d0xHd39ab4<0xHd39ab4_0=1.3._R:d0xHd39a98<0xHd39a98_R:d0xHd39a98>0xHd39a98_R:d0xHd39aa8>0xHd39aa8_R:d0xHd39aac>0xHd39aac_R:d0xHd39ab0>0xHd39ab0_R:d0xHd39ab4>0xHd39ab4_R:0xHd172a0!=0"
    },
    {
      "achievementId": 227909,
      "title": "Hard Notes",
      "description": "Earn a Tytanium from playing Kimpon's Minigame",
      "points": 5,
      "trueRatio": 15,
      "type": "",
      "author": "DoctorV",
      "badgeUrl": "https://media.retroachievements.org/Badge/386228.png",
      "numAwarded": 371,
      "numAwardedHardcore": 265,
      "displayOrder": 0,
      "memAddr": "N:d0xHd39a78>0xHd39a78_0xH1ffeba6=85.1._d0xHd39a8c<0xHd39a8c_R:d0xHd39a78<0xHd39a78_R:d0xHd39a8c>0xHd39a8c_R:0xHd172a0!=0_R:0xHd39a7a=0"
    },
    {
      "achievementId": 227910,
      "title": "Delicious!",
      "description": "Earn a Divine Stew from playing Gashapon's Minigame",
      "points": 5,
      "trueRatio": 19,
      "type": "",
      "author": "DoctorV",
      "badgeUrl": "https://media.retroachievements.org/Badge/386229.png",
      "numAwarded": 277,
      "numAwardedHardcore": 202,
      "displayOrder": 0,
      "memAddr": "N:d0xHd39aa8>0xHd39aa8_0xH1ffeba6=85.1._d0xHd39ad4<0xHd39ad4_R:d0xHd39aa8<0xHd39aa8_R:d0xHd39ad4>0xHd39ad4_R:0xHd172a0!=0_R:0xHd39aaa=0"
    },
    {
      "achievementId": 227911,
      "title": "Divine Forging",
      "description": "Earn a divine weapon from playing Kampon's Minigame",
      "points": 5,
      "trueRatio": 27,
      "type": "",
      "author": "DoctorV",
      "badgeUrl": "https://media.retroachievements.org/Badge/386230.png",
      "numAwarded": 179,
      "numAwardedHardcore": 136,
      "displayOrder": 0,
      "memAddr": "N:d0xHd39a90>0xHd39a90_0xH1ffeba6=85.1._A:d0xHd39b64_A:d0xHd39b8c_A:d0xHd39bb4_A:d0xHd39bdc_A:d0xHd39c04_A:d0xHd39c2c_A:d0xHd39c54_A:d0xHd39c7c_d0xHd39ca4=0_A:0xHd39b64_A:0xHd39b8c_A:0xHd39bb4_A:0xHd39bdc_A:0xHd39c04_A:0xHd39c2c_A:0xHd39c54_A:0xHd39c7c_0xHd39ca4=1_R:d0xHd39a90<0xHd39a90_R:0xHd39a92=0"
    },
    {
      "achievementId": 227912,
      "title": "Divine Collection",
      "description": "Earn all 9 divine weapons from Kampon's Minigame",
      "points": 50,
      "trueRatio": 345,
      "type": "",
      "author": "DoctorV",
      "badgeUrl": "https://media.retroachievements.org/Badge/386231.png",
      "numAwarded": 124,
      "numAwardedHardcore": 107,
      "displayOrder": 0,
      "memAddr": "N:d0xHd39a90>0xHd39a90_0xH1ffeba6=85.1._A:d0xHd39b64_A:d0xHd39b8c_A:d0xHd39bb4_A:d0xHd39bdc_A:d0xHd39c04_A:d0xHd39c2c_A:d0xHd39c54_A:d0xHd39c7c_d0xHd39ca4=8_A:0xHd39b64_A:0xHd39b8c_A:0xHd39bb4_A:0xHd39bdc_A:0xHd39c04_A:0xHd39c2c_A:0xHd39c54_A:0xHd39c7c_M:0xHd39ca4=9_R:d0xHd39a90<0xHd39a90_R:0xHd39a92=0"
    },
    {
      "achievementId": 227913,
      "title": "Cleaving Into Action",
      "description": "Create your first Tatepon",
      "points": 1,
      "trueRatio": 1,
      "type": "",
      "author": "DoctorV",
      "badgeUrl": "https://media.retroachievements.org/Badge/386232.png",
      "numAwarded": 1615,
      "numAwardedHardcore": 1035,
      "displayOrder": 0,
      "memAddr": "d0xHd1fd34<0xHd1fd34_d0xHd39b70<0xHd39b70SB:0xXd39e0c_d0xXd39e0c=120SB:0xXd39e0c_d0xXd39e0c=240SB:0xXd39e0c_d0xXd39e0c=360SB:0xXd39e0c_d0xXd39e0c=480SB:0xXd39e0c_d0xXd39e0c=600SB:0xXd39e0c_d0xXd39e0c=720SB:0xXd39e0c_d0xXd39e0c=840"
    },
    {
      "achievementId": 227914,
      "title": "Bullseye",
      "description": "Create your first Yumipon",
      "points": 2,
      "trueRatio": 3,
      "type": "",
      "author": "DoctorV",
      "badgeUrl": "https://media.retroachievements.org/Badge/386233.png",
      "numAwarded": 1122,
      "numAwardedHardcore": 742,
      "displayOrder": 0,
      "memAddr": "d0xHd1fd34<0xHd1fd34_d0xHd39bc0<0xHd39bc0SB:0xXd39e0c_d0xXd39e0c=150SB:0xXd39e0c_d0xXd39e0c=300SB:0xXd39e0c_d0xXd39e0c=450SB:0xXd39e0c_d0xXd39e0c=600SB:0xXd39e0c_d0xXd39e0c=750SB:0xXd39e0c_d0xXd39e0c=900SB:0xXd39e0c_d0xXd39e0c=1050"
    },
    {
      "achievementId": 227915,
      "title": "Riding to Battle",
      "description": "Create your first Kibapon",
      "points": 3,
      "trueRatio": 7,
      "type": "",
      "author": "DoctorV",
      "badgeUrl": "https://media.retroachievements.org/Badge/386234.png",
      "numAwarded": 488,
      "numAwardedHardcore": 335,
      "displayOrder": 0,
      "memAddr": "d0xHd1fd34<0xHd1fd34_d0xHd39be8<0xHd39be8SB:0xXd39e0c_d0xXd39e0c=200SB:0xXd39e0c_d0xXd39e0c=400SB:0xXd39e0c_d0xXd39e0c=600SB:0xXd39e0c_d0xXd39e0c=800SB:0xXd39e0c_d0xXd39e0c=1000SB:0xXd39e0c_d0xXd39e0c=1200SB:0xXd39e0c_d0xXd39e0c=1400"
    },
    {
      "achievementId": 227916,
      "title": "Brute Force",
      "description": "Create your first Dekapon",
      "points": 4,
      "trueRatio": 14,
      "type": "",
      "author": "DoctorV",
      "badgeUrl": "https://media.retroachievements.org/Badge/386235.png",
      "numAwarded": 320,
      "numAwardedHardcore": 218,
      "displayOrder": 0,
      "memAddr": "d0xHd1fd34<0xHd1fd34_d0xHd39c38<0xHd39c38SB:0xXd39e0c_d0xXd39e0c=250SB:0xXd39e0c_d0xXd39e0c=500SB:0xXd39e0c_d0xXd39e0c=750SB:0xXd39e0c_d0xXd39e0c=1000SB:0xXd39e0c_d0xXd39e0c=1250SB:0xXd39e0c_d0xXd39e0c=1500SB:0xXd39e0c_d0xXd39e0c=1750"
    },
    {
      "achievementId": 227917,
      "title": "Acoustic Weaponry",
      "description": "Create your first Megapon",
      "points": 5,
      "trueRatio": 20,
      "type": "",
      "author": "DoctorV",
      "badgeUrl": "https://media.retroachievements.org/Badge/386236.png",
      "numAwarded": 270,
      "numAwardedHardcore": 190,
      "displayOrder": 0,
      "memAddr": "d0xHd1fd34<0xHd1fd34_d0xHd39c60<0xHd39c60SB:0xXd39e0c_d0xXd39e0c=300SB:0xXd39e0c_d0xXd39e0c=600SB:0xXd39e0c_d0xXd39e0c=900SB:0xXd39e0c_d0xXd39e0c=1200SB:0xXd39e0c_d0xXd39e0c=1500SB:0xXd39e0c_d0xXd39e0c=1800SB:0xXd39e0c_d0xXd39e0c=2100"
    },
    {
      "achievementId": 227918,
      "title": "Rabbit Formation",
      "description": "Create a Pyokola Rarepon",
      "points": 1,
      "trueRatio": 1,
      "type": "",
      "author": "DoctorV",
      "badgeUrl": "https://media.retroachievements.org/Badge/386237.png",
      "numAwarded": 974,
      "numAwardedHardcore": 651,
      "displayOrder": 0,
      "memAddr": "d0xHd1fd34<0xHd1fd34SB:0xXd39e0c_d0xXd39e0c=160_d0xHd39b48<0xHd39b48SB:0xXd39e0c_d0xXd39e0c=240_d0xHd39b70<0xHd39b70SB:0xXd39e0c_d0xXd39e0c=300_d0xHd39bc0<0xHd39bc0SB:0xXd39e0c_d0xXd39e0c=400_d0xHd39be8<0xHd39be8SB:0xXd39e0c_d0xXd39e0c=500_d0xHd39c38<0xHd39c38SB:0xXd39e0c_d0xXd39e0c=600_d0xHd39c60<0xHd39c60"
    },
    {
      "achievementId": 227919,
      "title": "Frog Formation",
      "description": "Create a Gekolos Rarepon",
      "points": 2,
      "trueRatio": 4,
      "type": "",
      "author": "DoctorV",
      "badgeUrl": "https://media.retroachievements.org/Badge/386238.png",
      "numAwarded": 686,
      "numAwardedHardcore": 474,
      "displayOrder": 0,
      "memAddr": "d0xHd1fd34<0xHd1fd34SB:0xXd39e0c_d0xXd39e0c=240_d0xHd39b48<0xHd39b48SB:0xXd39e0c_d0xXd39e0c=360_d0xHd39b70<0xHd39b70SB:0xXd39e0c_d0xXd39e0c=450_d0xHd39bc0<0xHd39bc0SB:0xXd39e0c_d0xXd39e0c=600_d0xHd39be8<0xHd39be8SB:0xXd39e0c_d0xXd39e0c=750_d0xHd39c38<0xHd39c38SB:0xXd39e0c_d0xXd39e0c=900_d0xHd39c60<0xHd39c60"
    },
    {
      "achievementId": 227920,
      "title": "Ram Formation",
      "description": "Create a Mofeel Rarepon",
      "points": 3,
      "trueRatio": 7,
      "type": "",
      "author": "DoctorV",
      "badgeUrl": "https://media.retroachievements.org/Badge/386239.png",
      "numAwarded": 498,
      "numAwardedHardcore": 347,
      "displayOrder": 0,
      "memAddr": "d0xHd1fd34<0xHd1fd34SB:0xXd39e0c_d0xXd39e0c=320_d0xHd39b48<0xHd39b48SB:0xXd39e0c_d0xXd39e0c=480_d0xHd39b70<0xHd39b70SB:0xXd39e0c_d0xXd39e0c=600_d0xHd39bc0<0xHd39bc0SB:0xXd39e0c_d0xXd39e0c=800_d0xHd39be8<0xHd39be8SB:0xXd39e0c_d0xXd39e0c=1000_d0xHd39c38<0xHd39c38SB:0xXd39e0c_d0xXd39e0c=1200_d0xHd39c60<0xHd39c60"
    },
    {
      "achievementId": 227921,
      "title": "Hedgehog Formation",
      "description": "Create a Tikulee Rarepon",
      "points": 4,
      "trueRatio": 11,
      "type": "",
      "author": "DoctorV",
      "badgeUrl": "https://media.retroachievements.org/Badge/386240.png",
      "numAwarded": 433,
      "numAwardedHardcore": 299,
      "displayOrder": 0,
      "memAddr": "d0xHd1fd34<0xHd1fd34SB:0xXd39e0c_d0xXd39e0c=400_d0xHd39b48<0xHd39b48SB:0xXd39e0c_d0xXd39e0c=600_d0xHd39b70<0xHd39b70SB:0xXd39e0c_d0xXd39e0c=750_d0xHd39bc0<0xHd39bc0SB:0xXd39e0c_d0xXd39e0c=1000_d0xHd39be8<0xHd39be8SB:0xXd39e0c_d0xXd39e0c=1250_d0xHd39c38<0xHd39c38SB:0xXd39e0c_d0xXd39e0c=1500_d0xHd39c60<0xHd39c60"
    },
    {
      "achievementId": 227922,
      "title": "Bull Formation",
      "description": "Create a Mogyoon Rarepon",
      "points": 5,
      "trueRatio": 16,
      "type": "",
      "author": "DoctorV",
      "badgeUrl": "https://media.retroachievements.org/Badge/386241.png",
      "numAwarded": 369,
      "numAwardedHardcore": 245,
      "displayOrder": 0,
      "memAddr": "d0xHd1fd34<0xHd1fd34SB:0xXd39e0c_d0xXd39e0c=480_d0xHd39b48<0xHd39b48SB:0xXd39e0c_d0xXd39e0c=720_d0xHd39b70<0xHd39b70SB:0xXd39e0c_d0xXd39e0c=900_d0xHd39bc0<0xHd39bc0SB:0xXd39e0c_d0xXd39e0c=1200_d0xHd39be8<0xHd39be8SB:0xXd39e0c_d0xXd39e0c=1500_d0xHd39c38<0xHd39c38SB:0xXd39e0c_d0xXd39e0c=1800_d0xHd39c60<0xHd39c60"
    },
    {
      "achievementId": 227923,
      "title": "Bird Formation",
      "description": "Create a Barsala Rarepon",
      "points": 10,
      "trueRatio": 43,
      "type": "",
      "author": "DoctorV",
      "badgeUrl": "https://media.retroachievements.org/Badge/386242.png",
      "numAwarded": 258,
      "numAwardedHardcore": 182,
      "displayOrder": 0,
      "memAddr": "d0xHd1fd34<0xHd1fd34SB:0xXd39e0c_d0xXd39e0c=560_d0xHd39b48<0xHd39b48SB:0xXd39e0c_d0xXd39e0c=840_d0xHd39b70<0xHd39b70SB:0xXd39e0c_d0xXd39e0c=1050_d0xHd39bc0<0xHd39bc0SB:0xXd39e0c_d0xXd39e0c=1400_d0xHd39be8<0xHd39be8SB:0xXd39e0c_d0xXd39e0c=1750_d0xHd39c38<0xHd39c38SB:0xXd39e0c_d0xXd39e0c=2100_d0xHd39c60<0xHd39c60"
    },
    {
      "achievementId": 227924,
      "title": "Almighty Captain",
      "description": "Have a total of 12 units",
      "points": 5,
      "trueRatio": 9,
      "type": "",
      "author": "DoctorV",
      "badgeUrl": "https://media.retroachievements.org/Badge/386243.png",
      "numAwarded": 790,
      "numAwardedHardcore": 536,
      "displayOrder": 0,
      "memAddr": "d0xHd1fd34=11_0xHd1fd34=12"
    },
    {
      "achievementId": 227925,
      "title": "Almighty General",
      "description": "Have a total of 27 units",
      "points": 10,
      "trueRatio": 52,
      "type": "",
      "author": "DoctorV",
      "badgeUrl": "https://media.retroachievements.org/Badge/386244.png",
      "numAwarded": 209,
      "numAwardedHardcore": 145,
      "displayOrder": 0,
      "memAddr": "d0xHd1fd34=26_0xHd1fd34=27"
    },
    {
      "achievementId": 227926,
      "title": "Combo Commander",
      "description": "Get a Fever on the third combo on any mission",
      "points": 10,
      "trueRatio": 22,
      "type": "",
      "author": "DoctorV",
      "badgeUrl": "https://media.retroachievements.org/Badge/386245.png",
      "numAwarded": 601,
      "numAwardedHardcore": 415,
      "displayOrder": 0,
      "memAddr": "I:0xW00d12dc0_d0xH00f6c8a4=2_I:0xW00d12dc0_0xH00f6c8a4=25"
    },
    {
      "achievementId": 227927,
      "title": "March to the Beat",
      "description": "Stay in a Fever for one minute",
      "points": 5,
      "trueRatio": 8,
      "type": "",
      "author": "DoctorV",
      "badgeUrl": "https://media.retroachievements.org/Badge/386246.png",
      "numAwarded": 910,
      "numAwardedHardcore": 623,
      "displayOrder": 0,
      "memAddr": "I:0xW00d12dc0_N:0xH00f6c8a4=25_N:0xH00d56ae4=0_I:0xW00d12dc0_0xH00f6c8a4=25.3600._I:0xW00d12dc0_R:0xH00f6c8a4!=25"
    }
  ]
}