{
  "gameId": 409,
  "gameTitle": "Hagane: The Final Conflict",
  "achievements": [
    {
      "achievementId": 924,
      "title": "The Path to Disaster",
      "description": "Defeat Musha-Mukuro and clear 1st Stage",
      "points": 5,
      "trueRatio": 18,
      "type": "progression",
      "author": "Dissection",
      "badgeUrl": "https://media.retroachievements.org/Badge/124274.png",
      "numAwarded": 412,
      "numAwardedHardcore": 172,
      "displayOrder": 1,
      "memAddr": "0xH000500=1_0xH000504=2_0xH000505=1_0xM000531=0"
    },
    {
      "achievementId": 925,
      "title": "The Fortress of Doom",
      "description": "Defeat En-Mikosh and clear 2nd Stage",
      "points": 5,
      "trueRatio": 23,
      "type": "progression",
      "author": "Dissection",
      "badgeUrl": "https://media.retroachievements.org/Badge/124275.png",
      "numAwarded": 295,
      "numAwardedHardcore": 130,
      "displayOrder": 2,
      "memAddr": "0xH000500=2_0xH000504=3_0xH000505=1_0xM000531=0"
    },
    {
      "achievementId": 926,
      "title": "Violated Heavens",
      "description": "Defeat Jasei-Jyu and clear 3rd Stage",
      "points": 10,
      "trueRatio": 52,
      "type": "progression",
      "author": "Dissection",
      "badgeUrl": "https://media.retroachievements.org/Badge/124276.png",
      "numAwarded": 268,
      "numAwardedHardcore": 115,
      "displayOrder": 3,
      "memAddr": "0xH000500=3_0xH000504=4_0xH000505=1_0xM000531=0"
    },
    {
      "achievementId": 927,
      "title": "Cry of the Spirits",
      "description": "Defeat  Jyuso-Dama and clear 4th Stage",
      "points": 10,
      "trueRatio": 57,
      "type": "progression",
      "author": "Dissection",
      "badgeUrl": "https://media.retroachievements.org/Badge/124277.png",
      "numAwarded": 243,
      "numAwardedHardcore": 105,
      "displayOrder": 4,
      "memAddr": "0xH000500=4_0xH000504=5_0xH000505=1_0xM000531=0"
    },
    {
      "achievementId": 928,
      "title": "Koma Faction's Fall",
      "description": "Finish the Game",
      "points": 25,
      "trueRatio": 159,
      "type": "win_condition",
      "author": "Dissection",
      "badgeUrl": "https://media.retroachievements.org/Badge/124278.png",
      "numAwarded": 207,
      "numAwardedHardcore": 93,
      "displayOrder": 5,
      "memAddr": "0xH000500=0_0xH000501=0_0xH000506=5_0xH000507=1_0xH000504=5_0xH000505=7_0xM000531=0"
    },
    {
      "achievementId": 113784,
      "title": "Not So Disaster",
      "description": "Clear 1st stage deathless",
      "points": 10,
      "trueRatio": 74,
      "type": "",
      "author": "Shmelyoff",
      "badgeUrl": "https://media.retroachievements.org/Badge/124240.png",
      "numAwarded": 200,
      "numAwardedHardcore": 79,
      "displayOrder": 6,
      "memAddr": "T:0x 000504=1281_0x 000504=257.1._T:0x 000504=513.1._T:0x 000504=769.1._T:0x 000504=1025.1._T:d0x 000500=1792_T:0x 000500=1_R:0xH000515<d0xH000515_R:0xH000515=255_R:0x 000500=769_R:0xM000531!=0_R:0xH00050d=0_R:0xH0000d8=32"
    },
    {
      "achievementId": 113785,
      "title": "Storming The Fortress",
      "description": "Clear 2nd stage deathless",
      "points": 10,
      "trueRatio": 86,
      "type": "",
      "author": "Shmelyoff",
      "badgeUrl": "https://media.retroachievements.org/Badge/124241.png",
      "numAwarded": 185,
      "numAwardedHardcore": 67,
      "displayOrder": 7,
      "memAddr": "T:0x 000504=1026_0x 000504=258.1._T:0x 000504=514.1._T:0x 000504=770.1._T:d0x 000500=1793_T:0x 000500=2_R:0xH000515<d0xH000515_R:0xH000515=255_R:0x 000500=769_R:0xM000531!=0_R:0xH00050d=0_R:0xH0000d8=32"
    },
    {
      "achievementId": 113786,
      "title": "Blazing through the Skies",
      "description": "Clear 3rd stage deathless",
      "points": 10,
      "trueRatio": 89,
      "type": "",
      "author": "Shmelyoff",
      "badgeUrl": "https://media.retroachievements.org/Badge/124242.png",
      "numAwarded": 174,
      "numAwardedHardcore": 64,
      "displayOrder": 8,
      "memAddr": "T:0x 000504=1283_0x 000504=259.1._T:0x 000504=515.1._T:0x 000504=771.1._T:0x 000504=1027.1._T:d0x 000500=1794_T:0x 000500=3_R:0xH000515<d0xH000515_R:0xH000515=255_R:0x 000500=769_R:0xM000531!=0_R:0xH00050d=0_R:0xH0000d8=32"
    },
    {
      "achievementId": 113787,
      "title": "Imperturbable Cyborg",
      "description": "Clear 4th stage deathless",
      "points": 10,
      "trueRatio": 120,
      "type": "",
      "author": "Shmelyoff",
      "badgeUrl": "https://media.retroachievements.org/Badge/124243.png",
      "numAwarded": 123,
      "numAwardedHardcore": 47,
      "displayOrder": 9,
      "memAddr": "T:0x 000504=1028_0x 000504=260.1._T:0x 000504=516.1._T:0x 000504=772.1._T:d0x 000500=1795_T:0x 000500=4_R:0xH000515<d0xH000515_R:0xH000515=255_R:0x 000500=769_R:0xM000531!=0_R:0xH00050d=0_R:0xH0000d8=32"
    },
    {
      "achievementId": 113788,
      "title": "Lightbringer",
      "description": "Clear 5th stage deathless",
      "points": 25,
      "trueRatio": 388,
      "type": "",
      "author": "Shmelyoff",
      "badgeUrl": "https://media.retroachievements.org/Badge/124244.png",
      "numAwarded": 103,
      "numAwardedHardcore": 36,
      "displayOrder": 10,
      "memAddr": "T:0x 000504=1797_0x 000504=261.1._T:0x 000504=517.1._T:0x 000504=773.1._T:0x 000504=1029.1._T:0x 000504=1285.1._T:0x 000504=1541.1._T:d0x 000500=1797_T:0x 000500=6_R:0xH000515<d0xH000515_R:0xH000515=255_R:0x 000500=769_R:0xM000531!=0_R:0xH00050d=0_R:0xH0000d8=32"
    },
    {
      "achievementId": 113764,
      "title": "Way of Cyber Ninja",
      "description": "Finish the game without using continues",
      "points": 25,
      "trueRatio": 306,
      "type": "",
      "author": "Shmelyoff",
      "badgeUrl": "https://media.retroachievements.org/Badge/124255.png",
      "numAwarded": 117,
      "numAwardedHardcore": 46,
      "displayOrder": 11,
      "memAddr": "0xH000500=6_0xH000501=0_0xH000506=5_0xH000507=1_0xH000504=5_0xH000505=7_d0xH000507=0_0x 000504=257.1._R:0xH000515=255_0xM000531=0SN:0xH000504=1_d0xH000504=0.1.SN:0xH000504=1_d0xH000504=7.1."
    },
    {
      "achievementId": 113763,
      "title": "Bombless",
      "description": "Finish the game without using scrolls",
      "points": 25,
      "trueRatio": 410,
      "type": "",
      "author": "Shmelyoff",
      "badgeUrl": "https://media.retroachievements.org/Badge/124254.png",
      "numAwarded": 61,
      "numAwardedHardcore": 34,
      "displayOrder": 12,
      "memAddr": "0xH000500=6_0xH000501=0_0xH000506=5_0xH000507=1_0xH000504=5_0xH000505=7_d0xH000507=0_0x 000504=257.1._0xM000531=0_R:0xH0000a7=38_P:0x 000504=0SN:0xH000504=1_d0xH000504=0.1.SN:0xH000504=1_d0xH000504=7.1."
    },
    {
      "achievementId": 113762,
      "title": "Now This is the End for Real",
      "description": "Finish 2nd loop.",
      "points": 50,
      "trueRatio": 1063,
      "type": "",
      "author": "Shmelyoff",
      "badgeUrl": "https://media.retroachievements.org/Badge/124253.png",
      "numAwarded": 45,
      "numAwardedHardcore": 26,
      "displayOrder": 13,
      "memAddr": "0xH000500=6_0xH000501=0_0xH000506=5_0xH000507=1_0xH000504=5_0xH000505=7_0xH000532=1_d0xH000507=0_0xM000531=0"
    },
    {
      "achievementId": 58895,
      "title": "Max Shurikens",
      "description": "Collect 99 Shurikens",
      "points": 5,
      "trueRatio": 5,
      "type": "",
      "author": "sireture",
      "badgeUrl": "https://media.retroachievements.org/Badge/124272.png",
      "numAwarded": 2627,
      "numAwardedHardcore": 1179,
      "displayOrder": 14,
      "memAddr": "0xH000511=99_0xM000531=0"
    },
    {
      "achievementId": 58896,
      "title": "Max Byakko (Bombs)",
      "description": "Collect 99 Byakko (Bombs)",
      "points": 5,
      "trueRatio": 5,
      "type": "",
      "author": "sireture",
      "badgeUrl": "https://media.retroachievements.org/Badge/124273.png",
      "numAwarded": 2706,
      "numAwardedHardcore": 1196,
      "displayOrder": 15,
      "memAddr": "0xH000512=99_0xM000531=0"
    },
    {
      "achievementId": 113760,
      "title": "Fully Charged",
      "description": "Max up amount of lives",
      "points": 10,
      "trueRatio": 115,
      "type": "",
      "author": "Shmelyoff",
      "badgeUrl": "https://media.retroachievements.org/Badge/124125.png",
      "numAwarded": 132,
      "numAwardedHardcore": 49,
      "displayOrder": 16,
      "memAddr": "0xH000515=9_d0xH000515>=7_d0xH000515<=8_0xM000531=0"
    },
    {
      "achievementId": 113761,
      "title": "Ancient Cyber Magic Expert",
      "description": "Max up amount of spells",
      "points": 10,
      "trueRatio": 55,
      "type": "",
      "author": "Shmelyoff",
      "badgeUrl": "https://media.retroachievements.org/Badge/124126.png",
      "numAwarded": 199,
      "numAwardedHardcore": 109,
      "displayOrder": 17,
      "memAddr": "0xH000516=9_d0xH000516>=7_d0xH000516<=8_0xM000531=0"
    },
    {
      "achievementId": 113773,
      "title": "Reserving Power",
      "description": "Max up your HP",
      "points": 5,
      "trueRatio": 12,
      "type": "",
      "author": "Shmelyoff",
      "badgeUrl": "https://media.retroachievements.org/Badge/124132.png",
      "numAwarded": 577,
      "numAwardedHardcore": 292,
      "displayOrder": 18,
      "memAddr": "0xH000513=5_d0xH000513>=3_d0xH000513<=4_R:0xH000504=0_0xM000531=0"
    },
    {
      "achievementId": 113769,
      "title": "Lord of the Giants",
      "description": "Defeat Musha-Mukuro without taking damage (No bomb usage)",
      "points": 10,
      "trueRatio": 85,
      "type": "",
      "author": "Shmelyoff",
      "badgeUrl": "https://media.retroachievements.org/Badge/124252.png",
      "numAwarded": 124,
      "numAwardedHardcore": 68,
      "displayOrder": 19,
      "memAddr": "R:0x 000504!=1281_R:0xH000516<d0xH000516_R:0xH000514<d0xH000514_R:0xH000903!=0_R:0xH0000a7=38_T:d0xH0011af=50.1._T:d0x 000500=1792_T:0x 000500=1_R:0x 000500=769Sd0x 000504=1025.1.S0xH000515<d0xH000515.1.Sd0x 000504=1282.1."
    },
    {
      "achievementId": 113782,
      "title": "Get Over Here!",
      "description": "Defeat mid-boss on stage 2-1 dealing damage only with grappling hook without taking damage",
      "points": 10,
      "trueRatio": 91,
      "type": "",
      "author": "Shmelyoff",
      "badgeUrl": "https://media.retroachievements.org/Badge/124188.png",
      "numAwarded": 93,
      "numAwardedHardcore": 63,
      "displayOrder": 20,
      "memAddr": "R:0xH000516<d0xH000516_R:0xH000514<d0xH000514_R:0xH000903!=0_R:0xH0000a7=38_R:0x 000504!=258_T:0x 000500=257_T:d0x 000500=1_T:0xH00122f=36.1._N:0xH00122f<d0xH00122f_R:0xH000918>8_N:0xH00122f<d0xH00122f_R:0xH00050f!=3_N:0xH00122f<d0xH00122f_N:0xH000918>0_R:0xH000918<5Sd0x 000504=1281.1.Sd0x 000504=1282.1.S0xH000515<d0xH000515.1.Sd0x 000504=0.1."
    },
    {
      "achievementId": 113771,
      "title": "Core of Evil",
      "description": "Defeat En-Mikoshi without taking damage (No bomb usage)",
      "points": 10,
      "trueRatio": 111,
      "type": "",
      "author": "Shmelyoff",
      "badgeUrl": "https://media.retroachievements.org/Badge/124251.png",
      "numAwarded": 99,
      "numAwardedHardcore": 51,
      "displayOrder": 21,
      "memAddr": "R:0x 000504!=1026_R:0xH000516<d0xH000516_R:0xH000514<d0xH000514_R:0xH000903!=0_R:0xH0000a7=38_T:d0xH00112f=40.1._T:d0x 000500=1793_T:0x 000500=2_R:0x 000500=769Sd0x 000504=770.1.S0xH000515<d0xH000515.1.Sd0x 000504=1282.1."
    },
    {
      "achievementId": 113775,
      "title": "Longma",
      "description": "Defeat Jasei-Jyu without taking damage (No bomb usage)",
      "points": 25,
      "trueRatio": 512,
      "type": "",
      "author": "Shmelyoff",
      "badgeUrl": "https://media.retroachievements.org/Badge/124249.png",
      "numAwarded": 59,
      "numAwardedHardcore": 27,
      "displayOrder": 22,
      "memAddr": "R:0x 000504!=1283_R:0xH000516<d0xH000516_R:0xH000514<d0xH000514_R:0xH000903!=0_R:0xH0000a7=38_T:d0xH0011af=60.1._T:d0x 000500=1794_T:0x 000500=3_R:0x 000500=769Sd0x 000504=1027.1.S0xH000515<d0xH000515.1.Sd0x 000504=1282.1."
    },
    {
      "achievementId": 113776,
      "title": "Serpentologist",
      "description": "Kill snake in stage 4-2 using up kick without taking damage",
      "points": 5,
      "trueRatio": 86,
      "type": "",
      "author": "Shmelyoff",
      "badgeUrl": "https://media.retroachievements.org/Badge/124256.png",
      "numAwarded": 48,
      "numAwardedHardcore": 32,
      "displayOrder": 23,
      "memAddr": "R:0xH000514<d0xH000514_R:0x 000504!=516_R:0x 0007a8!=2560_R:0x 0007ae!=768_d0x 0007a8>2560.1._N:0xH000906=29_T:0xH00051e!=d0xH00051e"
    },
    {
      "achievementId": 113777,
      "title": "No Place for Old Man",
      "description": "Defeat Jyuso-Dama without taking damage (No bomb usage)",
      "points": 10,
      "trueRatio": 159,
      "type": "",
      "author": "Shmelyoff",
      "badgeUrl": "https://media.retroachievements.org/Badge/124248.png",
      "numAwarded": 63,
      "numAwardedHardcore": 35,
      "displayOrder": 24,
      "memAddr": "R:0x 000504!=1028_R:0xH000516<d0xH000516_R:0xH000514<d0xH000514_R:0xH000903!=0_R:0xH0000a7=38_T:d0xH00102f=50.1._T:d0x 000500=1795_T:0x 000500=4_R:0x 000500=769Sd0x 000504=772.1.S0xH000515<d0xH000515.1.Sd0x 000504=1282.1."
    },
    {
      "achievementId": 113778,
      "title": "One Shot One Hit",
      "description": "Kill mid-boss on stage 5-3 with single hit without taking damage",
      "points": 5,
      "trueRatio": 82,
      "type": "",
      "author": "Shmelyoff",
      "badgeUrl": "https://media.retroachievements.org/Badge/124247.png",
      "numAwarded": 47,
      "numAwardedHardcore": 34,
      "displayOrder": 25,
      "memAddr": "R:0xH000514<d0xH000514_R:0x 000504!=773_N:0xH000906=29_N:0xH00051e!=d0xH00051e_N:0xH00102f=255_T:d0xH00102f=24Sd0x 000504=517.1.Sd0x 000504=1282.1.S0xH000515<d0xH000515.1."
    },
    {
      "achievementId": 113779,
      "title": "Illusion of Might",
      "description": "Defeat Shurb-Oh without taking damage (No bomb usage)",
      "points": 10,
      "trueRatio": 133,
      "type": "",
      "author": "Shmelyoff",
      "badgeUrl": "https://media.retroachievements.org/Badge/124246.png",
      "numAwarded": 79,
      "numAwardedHardcore": 42,
      "displayOrder": 26,
      "memAddr": "R:0xH000516<d0xH000516_R:0xH000514<d0xH000514_R:0xH000903!=0_R:0xH0000a7=38_R:0x 000504!=1541_T:0x 000500=1797_T:d0x 000500=1796_T:0xH00102f=30.1._R:0x 000500=769Sd0x 000504=1285.1.Sd0x 000504=1282.1.S0xH000515<d0xH000515.1."
    },
    {
      "achievementId": 113765,
      "title": "On the Top of the World",
      "description": "Defeat Amano-Ikazuchi standing on top tower platform",
      "points": 10,
      "trueRatio": 220,
      "type": "",
      "author": "Shmelyoff",
      "badgeUrl": "https://media.retroachievements.org/Badge/124127.png",
      "numAwarded": 46,
      "numAwardedHardcore": 25,
      "displayOrder": 27,
      "memAddr": "0xH000500=6_0xH000501=0_0xH000506=5_0xH000507=1_0xH000504=5_0xH000505=7_d0xH000507=0_0x 0007ae<=1048_0x 0007ae!=0"
    },
    {
      "achievementId": 113772,
      "title": "Jitsu Master",
      "description": "Successfully kill at least 1 enemy using every jitsu without dying",
      "points": 5,
      "trueRatio": 56,
      "type": "",
      "author": "Shmelyoff",
      "badgeUrl": "https://media.retroachievements.org/Badge/124129.png",
      "numAwarded": 79,
      "numAwardedHardcore": 50,
      "displayOrder": 28,
      "memAddr": "R:0xH000515<d0xH000515_R:0xH000515=255_N:0xH000906=24_0xH00051d!=d0xH00051d.1._N:0xH000906=25_0xH00051d!=d0xH00051d.1._N:0xH000906=26_0xH00051d!=d0xH00051d.1._N:0xH000906=27_0xH00051d!=d0xH00051d.1._N:0xH000906=28_0xH00051d!=d0xH00051d.1._N:0xH000906=29_0xH00051d!=d0xH00051d.1."
    },
    {
      "achievementId": 113766,
      "title": "Search Mode Activated I",
      "description": "Find 1up on stage 1-2",
      "points": 5,
      "trueRatio": 54,
      "type": "",
      "author": "Shmelyoff",
      "badgeUrl": "https://media.retroachievements.org/Badge/124114.png",
      "numAwarded": 83,
      "numAwardedHardcore": 52,
      "displayOrder": 29,
      "memAddr": "0x 000504=513_0x 0007a8<=1196_0x 0007a8>=1072_0x 0007ae>=256_0x 0007ae<=336_0xH0000a7=34_0xM000531=0"
    },
    {
      "achievementId": 113780,
      "title": "Search Mode Activated II",
      "description": "Find 1up on stage 4-1",
      "points": 5,
      "trueRatio": 68,
      "type": "",
      "author": "Shmelyoff",
      "badgeUrl": "https://media.retroachievements.org/Badge/124118.png",
      "numAwarded": 56,
      "numAwardedHardcore": 41,
      "displayOrder": 30,
      "memAddr": "N:0xH0000a7=34_d0xH0000a7!=34_0x 000504=260_0x 0007a8>=1558_0x 0007ae<=512_0x 0007a8<=1632_0xM000531=0"
    },
    {
      "achievementId": 113767,
      "title": "Search Mode Activated III",
      "description": "Get to the power up section on stage 4-3",
      "points": 5,
      "trueRatio": 106,
      "type": "",
      "author": "Shmelyoff",
      "badgeUrl": "https://media.retroachievements.org/Badge/124116.png",
      "numAwarded": 53,
      "numAwardedHardcore": 26,
      "displayOrder": 31,
      "memAddr": "0x 000504=772_0x 0007a8<=1048_0x 0007a8>=907_0x 0007ae>=282_0x 0007ae<=312_0xH0000a7=34_0xM000531=0"
    },
    {
      "achievementId": 113768,
      "title": "Worm Rider",
      "description": "Finish stage 1-3 with at least 225 seconds remaining",
      "points": 10,
      "trueRatio": 239,
      "type": "",
      "author": "Shmelyoff",
      "badgeUrl": "https://media.retroachievements.org/Badge/124211.png",
      "numAwarded": 66,
      "numAwardedHardcore": 23,
      "displayOrder": 32,
      "memAddr": "0x 00007b>=549_0x 000504=769_0x 000500=768_d0x 000500=512"
    },
    {
      "achievementId": 113770,
      "title": "Factory Runner",
      "description": "Finish stage 2-2 with at least 150 seconds remaining",
      "points": 10,
      "trueRatio": 220,
      "type": "",
      "author": "Shmelyoff",
      "badgeUrl": "https://media.retroachievements.org/Badge/124213.png",
      "numAwarded": 61,
      "numAwardedHardcore": 25,
      "displayOrder": 33,
      "memAddr": "0x 00007b>=336_0x 000504=514_d0x 000500=257_0x 000500=513"
    },
    {
      "achievementId": 113783,
      "title": "Jumping on their Heads",
      "description": "Finish stage 4-3 with at least 205 seconds remaining",
      "points": 10,
      "trueRatio": 261,
      "type": "",
      "author": "Shmelyoff",
      "badgeUrl": "https://media.retroachievements.org/Badge/124245.png",
      "numAwarded": 53,
      "numAwardedHardcore": 21,
      "displayOrder": 34,
      "memAddr": "0x 00007b>=517_0x 000504=772_d0x 000500=771_0x 000500=1795"
    },
    {
      "achievementId": 113781,
      "title": "Running Through Facility",
      "description": "Finish stage 5-2 with at least 185 seconds remaining",
      "points": 5,
      "trueRatio": 114,
      "type": "",
      "author": "Shmelyoff",
      "badgeUrl": "https://media.retroachievements.org/Badge/124219.png",
      "numAwarded": 38,
      "numAwardedHardcore": 24,
      "displayOrder": 35,
      "memAddr": "0x 00007b>=389_0x 000504=517_d0x 000500=260_0x 000500=773"
    },
    {
      "achievementId": 113774,
      "title": "Waste of Resources not Appropriate",
      "description": "Pick up 17 drops on stage 3-3 without dying",
      "points": 10,
      "trueRatio": 197,
      "type": "",
      "author": "Shmelyoff",
      "badgeUrl": "https://media.retroachievements.org/Badge/124250.png",
      "numAwarded": 43,
      "numAwardedHardcore": 28,
      "displayOrder": 36,
      "memAddr": "R:0x 000500=769_R:0x 000504!=771_R:0xH000514=0_N:0xH0000a7=34_T:d0xH0000a7!=34.17.Sd0x 000504=515.1.S0xH000515<d0xH000515.1.Sd0x 000504=1282.1."
    }
  ]
}